argmark/__init__.py
argmark/argmark.py
argmark-0.3.dist-info/LICENSE
argmark-0.3.dist-info/METADATA
argmark-0.3.dist-info/WHEEL
argmark-0.3.dist-info/entry_points.txt
argmark-0.3.dist-info/top_level.txt
argmark-0.3.dist-info/RECORD
