Metadata-Version: 2.1
Name: argmark
Version: 0.3
Summary: Convert argparse based executable scripts to markdown documents.
Home-page: https://github.com/devanshkv/argmark
Author: Devansh Agarwal
Author-email: devansh.kv@gmail.com
License: UNKNOWN
Platform: UNKNOWN
Classifier: Programming Language :: Python :: 3.6
Classifier: Programming Language :: Python :: 3.7
Classifier: Programming Language :: Python :: 3.8
Classifier: Programming Language :: Python :: 3.9
Classifier: Topic :: Documentation
Classifier: License :: OSI Approved :: MIT License
Classifier: Natural Language :: English
Requires-Dist: mdutils (>=1.2.2)
Requires-Dist: setuptools (>=46.4.0.post20200518)
